<?xml version="1.0" encoding="utf-8"?>
<repository name="13th VAC OvGME Repository"
            baseUrl="https://github.com/13th-VAC/Repo-SG/releases/download/v1/">

  <mod name="13th_MANDATORY_476th_Range_Targets" version="1.0.0"
       url="13th_MANDATORY_476th Range Targets.zip">
  </mod>

  <mod name="13th_MANDATORY_HiDigitSAMs" version="2.1.0"
       url="13th_MANDATORY_HiDigitSAMs.zip">
    High Digit Sam ver 2.1.0
  </mod>

  <mod name="13th_MANDATORY_Insurgency_Pack" version="1.0.4"
       url="13th_MANDATORY_Insurgency_Pack.zip">
    This mod adds a number of insurgent vehicles and objects to DCS World.
    Models are licensed for non-commercial distribution.
  </mod>

  <mod name="13th_MANDATORY_VFA-242_Skins" version="1.1.2"
       url="13th_MANDATORY_VFA-242_Skins.zip">
    Added LoVis skins, updated HiVis tank skin.
  </mod>

  <mod name="13th_OPTIONAL_UH60L" version="1.4.0"
       url="13th_OPTIONAL_UH60L.zip">
    UH-60L Blackhawk Ver 1.4.0
  </mod>

</repository>

